{
  "page_number": 30,
  "ocr_output": {
    "blocks": [
      {
        "block_text": "വസ്തുനികുതി സ്വീകരിക്കുന്നത്",
        "lines": [
          "വസ്തുനികുതി സ്വീകരിക്കുന്നത്"
        ],
        "bounding_box": [
          {
            "x": 16,
            "y": 16
          },
          {
            "x": 394,
            "y": 16
          },
          {
            "x": 394,
            "y": 42
          },
          {
            "x": 16,
            "y": 42
          }
        ],
        "confidence": 0.86291724
      }
    ]
  }
}