{
  "page_number": 198,
  "ocr_output": {
    "blocks": [
      {
        "block_text": "( B ) കുറുനരികളുടെ ധൈര്യം",
        "lines": [
          "( B ) കുറുനരികളുടെ ധൈര്യം"
        ],
        "bounding_box": [
          {
            "x": 476,
            "y": 3
          },
          {
            "x": 837,
            "y": 2
          },
          {
            "x": 837,
            "y": 36
          },
          {
            "x": 476,
            "y": 37
          }
        ],
        "confidence": 0.9400023
      },
      {
        "block_text": "( A ) വിജന പരിസരത്തെ",
        "lines": [
          "( A ) വിജന പരിസരത്തെ"
        ],
        "bounding_box": [
          {
            "x": 6,
            "y": 7
          },
          {
            "x": 275,
            "y": 7
          },
          {
            "x": 275,
            "y": 30
          },
          {
            "x": 6,
            "y": 30
          }
        ],
        "confidence": 0.6792772
      },
      {
        "block_text": "( C ) ശാപ്പാടിലുള്ള ആവേശത്തെ",
        "lines": [
          "( C ) ശാപ്പാടിലുള്ള ആവേശത്തെ"
        ],
        "bounding_box": [
          {
            "x": 6,
            "y": 50
          },
          {
            "x": 357,
            "y": 50
          },
          {
            "x": 357,
            "y": 76
          },
          {
            "x": 6,
            "y": 76
          }
        ],
        "confidence": 0.78616756
      },
      {
        "block_text": "( D ) ഭീകരാന്തരീക്ഷത്തെ",
        "lines": [
          "( D ) ഭീകരാന്തരീക്ഷത്തെ"
        ],
        "bounding_box": [
          {
            "x": 478,
            "y": 50
          },
          {
            "x": 750,
            "y": 50
          },
          {
            "x": 750,
            "y": 73
          },
          {
            "x": 478,
            "y": 73
          }
        ],
        "confidence": 0.8732094
      }
    ]
  }
}