{
  "page_number": 839,
  "ocr_output": {
    "blocks": [
      {
        "block_text": "জনিউলায় ক্যাটার্যাক্টকে দুই শ্রেণীতে বিভক্ত করা যাইতে পারে । ১ ষ্টেনারি ( Stationary )  ায়ী । ২ প্রোগ্রেসিভ ( Progressive ) বা ক্রমবন্ধিত । প্রথমোক্ত শ্রেণীতে অক্ষিমূকুরের স্বপ্নাংশ আক্রান্ত হয় এবং ঐ রূপ অস্বচ্ছতার সীমা বিলক্ষণ নিদ্দিষ্ট ও অক্ষিমুকুরের পরিধিদেশ সম্পূর্ণ স্বচ্ছ থাকে । জনিউলার ক্যাটার্যাক্ট রোগে যদি এবম্বিধ পূর্ব্বোক্ত লক্ষণ সকল বর্তমান থাকে , তাহা হইলে নিশ্চয়ই বহুকাল বা জীবনাবধি ঐরূপ অস্বচ্ছতা বৰ্দ্ধিত হইবে না । অন্য পক্ষে যদি কৈন্দ্রিক অস্বচ্ছতার সঙ্গে সঙ্গে লেসের পরিধি মধ্যে ক্ষুদ্র ক্ষুদ্র অস্বচ্ছ বিন্দু বা স্ত্রী অর্থাৎ রেখা দৃষ্ট হয় , তাহা হইলে এরূপ ক্যাটার্যাক্ট ; নিশ্চয়ই বৃদ্ধি হইবে । এবম্বিধ স্থলে রোগের স্বভাবাহু- সারে চিকিৎসা প্রণালী অবলম্বন করা উচিত । পার্শ্ববর্তী আলোক দ্বারা পরীক্ষা করিলে কটিক্যাল , পদার্থস্থ দাগ ও রেখা সমূহ উত্তমরূপে দৃষ্ট হয় ।",
        "lines": [
          "জনিউলায় ক্যাটার্যাক্টকে দুই শ্রেণীতে বিভক্ত করা যাইতে পারে । ১ ষ্টেনারি ( Stationary )  ায়ী । ২ প্রোগ্রেসিভ ( Progressive ) বা ক্রমবন্ধিত । প্রথমোক্ত শ্রেণীতে অক্ষিমূকুরের স্বপ্নাংশ আক্রান্ত হয় এবং ঐ রূপ অস্বচ্ছতার সীমা বিলক্ষণ নিদ্দিষ্ট ও অক্ষিমুকুরের পরিধিদেশ সম্পূর্ণ স্বচ্ছ থাকে । জনিউলার ক্যাটার্যাক্ট রোগে যদি এবম্বিধ পূর্ব্বোক্ত লক্ষণ সকল বর্তমান থাকে , তাহা হইলে নিশ্চয়ই বহুকাল বা জীবনাবধি ঐরূপ অস্বচ্ছতা বৰ্দ্ধিত হইবে না । অন্য পক্ষে যদি কৈন্দ্রিক অস্বচ্ছতার সঙ্গে সঙ্গে লেসের পরিধি মধ্যে ক্ষুদ্র ক্ষুদ্র অস্বচ্ছ বিন্দু বা স্ত্রী অর্থাৎ রেখা দৃষ্ট হয় , তাহা হইলে এরূপ ক্যাটার্যাক্ট ; নিশ্চয়ই বৃদ্ধি হইবে । এবম্বিধ স্থলে রোগের স্বভাবাহু- সারে চিকিৎসা প্রণালী অবলম্বন করা উচিত । পার্শ্ববর্তী আলোক দ্বারা পরীক্ষা করিলে কটিক্যাল , পদার্থস্থ দাগ ও রেখা সমূহ উত্তমরূপে দৃষ্ট হয় ।"
        ],
        "bounding_box": [
          {
            "x": 2,
            "y": 5
          },
          {
            "x": 587,
            "y": 3
          },
          {
            "x": 588,
            "y": 373
          },
          {
            "x": 3,
            "y": 375
          }
        ],
        "confidence": 0.9496839
      }
    ]
  }
}