{
  "page_number": 457,
  "ocr_output": {
    "blocks": [
      {
        "block_text": "( ১৫ শ , প্রতিক্বতি দেখ ) । ফর্সেস দ্বারা",
        "lines": [
          "( ১৫ শ , প্রতিক্বতি দেখ ) । ফর্সেস দ্বারা"
        ],
        "bounding_box": [
          {
            "x": 20,
            "y": 5
          },
          {
            "x": 357,
            "y": 4
          },
          {
            "x": 357,
            "y": 27
          },
          {
            "x": 20,
            "y": 28
          }
        ],
        "confidence": 0.91657704
      },
      {
        "block_text": "ধরিলে পা গুলি সেই পরিমাণে চৰ্ম্ম",
        "lines": [
          "ধরিলে পা গুলি সেই পরিমাণে চৰ্ম্ম"
        ],
        "bounding_box": [
          {
            "x": 174,
            "y": 39
          },
          {
            "x": 360,
            "y": 35
          },
          {
            "x": 360,
            "y": 90
          },
          {
            "x": 175,
            "y": 94
          }
        ],
        "confidence": 0.94690293
      },
      {
        "block_text": "ছেদন করা আবশ্যক ; ইহা বুঝিয়া , এণ্টে । পিয়ামের বক্রতানুসারে কত পরিমাণে",
        "lines": [
          "ছেদন করা আবশ্যক ; ইহা বুঝিয়া , এণ্টে । পিয়ামের বক্রতানুসারে কত পরিমাণে"
        ],
        "bounding_box": [
          {
            "x": 16,
            "y": 104
          },
          {
            "x": 350,
            "y": 106
          },
          {
            "x": 350,
            "y": 163
          },
          {
            "x": 16,
            "y": 161
          }
        ],
        "confidence": 0.9518988
      },
      {
        "block_text": "চন্দ্র ছেদন করা আবশ্যক তাহা জানা যাইতে পারে । অপিচ , যাহাতে পাংটা আঘাতিত না হয় , তৎপক্ষে সতর্ক হওয়া",
        "lines": [
          "চন্দ্র ছেদন করা আবশ্যক তাহা জানা যাইতে পারে । অপিচ , যাহাতে পাংটা আঘাতিত না হয় , তৎপক্ষে সতর্ক হওয়া"
        ],
        "bounding_box": [
          {
            "x": 16,
            "y": 173
          },
          {
            "x": 351,
            "y": 175
          },
          {
            "x": 350,
            "y": 266
          },
          {
            "x": 15,
            "y": 264
          }
        ],
        "confidence": 0.9558214
      }
    ]
  }
}