{
  "page_number": 619,
  "ocr_output": {
    "blocks": [
      {
        "block_text": "সেন , প্রবো dQaz রবীন্দ্রনাথের শিক্ষাচিন্তা z LmL ja j x f h % IjSÉf bLf o 2007z ¢ xl z",
        "lines": [
          "সেন , প্রবো dQaz রবীন্দ্রনাথের শিক্ষাচিন্তা z LmL ja j x f h % IjSÉf bLf o 2007z ¢ xl z"
        ],
        "bounding_box": [
          {
            "x": 7,
            "y": 37
          },
          {
            "x": 850,
            "y": 35
          },
          {
            "x": 850,
            "y": 121
          },
          {
            "x": 7,
            "y": 123
          }
        ],
        "confidence": 0.81620955
      },
      {
        "block_text": "সেন , সুকুমার । বাঙ্গালা সাহিত্যের ইতিহাস ৩ য় খন্ড z LmLja j x Bea f jh ¢ mjpÑ 1350 z ¢ xl z",
        "lines": [
          "সেন , সুকুমার । বাঙ্গালা সাহিত্যের ইতিহাস ৩ য় খন্ড z LmLja j x Bea f jh ¢ mjpÑ 1350 z ¢ xl z"
        ],
        "bounding_box": [
          {
            "x": 7,
            "y": 178
          },
          {
            "x": 887,
            "y": 176
          },
          {
            "x": 887,
            "y": 260
          },
          {
            "x": 7,
            "y": 262
          }
        ],
        "confidence": 0.91289103
      },
      {
        "block_text": "সেন , সুকুমার । বাঙ্গালা সাহিত্যের ইতিহাস ৪ র্থ খন্ড z LmLja i x CoZN jhamp 1976 z ¢ l z",
        "lines": [
          "সেন , সুকুমার । বাঙ্গালা সাহিত্যের ইতিহাস ৪ র্থ খন্ড z LmLja i x CoZN jhamp 1976 z ¢ l z"
        ],
        "bounding_box": [
          {
            "x": 8,
            "y": 317
          },
          {
            "x": 867,
            "y": 315
          },
          {
            "x": 867,
            "y": 398
          },
          {
            "x": 8,
            "y": 400
          }
        ],
        "confidence": 0.8705851
      },
      {
        "block_text": "সেন , সুকুমার । বাঙ্গালা সাহিত্যের ইতিহাস ৫ ম খন্ড z LmLja j x Beaf jh ¢ mjpÑ 1365 z ¢ l z",
        "lines": [
          "সেন , সুকুমার । বাঙ্গালা সাহিত্যের ইতিহাস ৫ ম খন্ড z LmLja j x Beaf jh ¢ mjpÑ 1365 z ¢ l z"
        ],
        "bounding_box": [
          {
            "x": 8,
            "y": 456
          },
          {
            "x": 886,
            "y": 452
          },
          {
            "x": 886,
            "y": 536
          },
          {
            "x": 8,
            "y": 540
          }
        ],
        "confidence": 0.8902609
      },
      {
        "block_text": "সেনগুপ্ত , অচিন্ত্যকুমার । কল্লোলযুগ z LmLja i x Hj p . plLil Atta pep f ¢ n , 1357 z ¢ l z",
        "lines": [
          "সেনগুপ্ত , অচিন্ত্যকুমার । কল্লোলযুগ z LmLja i x Hj p . plLil Atta pep f ¢ n , 1357 z ¢ l z"
        ],
        "bounding_box": [
          {
            "x": 7,
            "y": 596
          },
          {
            "x": 853,
            "y": 586
          },
          {
            "x": 854,
            "y": 674
          },
          {
            "x": 8,
            "y": 684
          }
        ],
        "confidence": 0.8286715
      },
      {
        "block_text": "সেনগুপ্ত , গীতশ্রীবন্দনা । স্পন্দিত আন্তর্লোক - আত্মচরিতে নারী প্রগতির ধারা z কলকাতা : পগ্রে pi f jhamp 1999 z ¢ l z",
        "lines": [
          "সেনগুপ্ত , গীতশ্রীবন্দনা । স্পন্দিত আন্তর্লোক - আত্মচরিতে নারী প্রগতির ধারা z কলকাতা : পগ্রে pi f jhamp 1999 z ¢ l z"
        ],
        "bounding_box": [
          {
            "x": 5,
            "y": 731
          },
          {
            "x": 879,
            "y": 731
          },
          {
            "x": 879,
            "y": 824
          },
          {
            "x": 5,
            "y": 824
          }
        ],
        "confidence": 0.9091908
      },
      {
        "block_text": "সেনগুপ্ত , মল্লিকা । Unto ej z LmL ja j x Bea f jh ¢ m jpÑ1994 z ¢ l z",
        "lines": [
          "সেনগুপ্ত , মল্লিকা । Unto ej z LmL ja j x Bea f jh ¢ m jpÑ1994 z ¢ l z"
        ],
        "bounding_box": [
          {
            "x": 7,
            "y": 873
          },
          {
            "x": 867,
            "y": 873
          },
          {
            "x": 867,
            "y": 906
          },
          {
            "x": 7,
            "y": 906
          }
        ],
        "confidence": 0.7616293
      },
      {
        "block_text": "হালদার , শ্রী গৌরদাস । শিক্ষণ প্রসঙ্গে শিক্ষার ইতিহাস z LmLjai x hejSÐ | f jhæmjpÑ1987 z ¢ l z",
        "lines": [
          "হালদার , শ্রী গৌরদাস । শিক্ষণ প্রসঙ্গে শিক্ষার ইতিহাস z LmLjai x hejSÐ | f jhæmjpÑ1987 z ¢ l z"
        ],
        "bounding_box": [
          {
            "x": 7,
            "y": 953
          },
          {
            "x": 886,
            "y": 950
          },
          {
            "x": 886,
            "y": 1041
          },
          {
            "x": 7,
            "y": 1044
          }
        ],
        "confidence": 0.847399
      },
      {
        "block_text": "হালদার , গোপাল । বাংলা সাহিত্যের রূপ - রেখা ২ য় খন্ড z Lmja i x Al ¥ Zi f ējne £ 1401 z ¢ l z",
        "lines": [
          "হালদার , গোপাল । বাংলা সাহিত্যের রূপ - রেখা ২ য় খন্ড z Lmja i x Al ¥ Zi f ējne £ 1401 z ¢ l z"
        ],
        "bounding_box": [
          {
            "x": 8,
            "y": 1094
          },
          {
            "x": 875,
            "y": 1094
          },
          {
            "x": 875,
            "y": 1180
          },
          {
            "x": 8,
            "y": 1180
          }
        ],
        "confidence": 0.88194513
      }
    ]
  }
}