{
  "page_number": 822,
  "ocr_output": {
    "blocks": [
      {
        "block_text": "લેખકનું ઇંગ્લેન્ડ દર્શન આહ્લાદક છે . એટલે ગ્રાસમિઅરમાં આવેલા મહાન કવિ વર્ડ્ઝવર્થનો સંદર્ભ ટાંકીને માર્ટિન અને એરિકાના પ્રવાસ સાથે એ ઘટનાને જોડે છે . પાત્રોના",
        "lines": [
          "લેખકનું ઇંગ્લેન્ડ દર્શન આહ્લાદક છે . એટલે ગ્રાસમિઅરમાં આવેલા મહાન કવિ વર્ડ્ઝવર્થનો સંદર્ભ ટાંકીને માર્ટિન અને એરિકાના પ્રવાસ સાથે એ ઘટનાને જોડે છે . પાત્રોના"
        ],
        "bounding_box": [
          {
            "x": 13,
            "y": 8
          },
          {
            "x": 878,
            "y": 8
          },
          {
            "x": 878,
            "y": 99
          },
          {
            "x": 13,
            "y": 99
          }
        ],
        "confidence": 1
      },
      {
        "block_text": "નામો એરિકા એ પણ કવિ એરિક ફોમ સાથેનો તેમજ માર્ટિનનો સંદર્ભ વિચારક્રાન્તિના પ્રણેતા માર્ટિન લ્યુથર કિંગને લઈને મહાન કવિની સ્મૃતિને તેઓ વાગોળતા હોય એવું આલેખન આ લઘુનવલમાં લેખકે કર્યું છે .",
        "lines": [
          "નામો એરિકા એ પણ કવિ એરિક ફોમ સાથેનો તેમજ માર્ટિનનો સંદર્ભ વિચારક્રાન્તિના પ્રણેતા માર્ટિન લ્યુથર કિંગને લઈને મહાન કવિની સ્મૃતિને તેઓ વાગોળતા હોય એવું આલેખન આ લઘુનવલમાં લેખકે કર્યું છે ."
        ],
        "bounding_box": [
          {
            "x": 13,
            "y": 117
          },
          {
            "x": 878,
            "y": 120
          },
          {
            "x": 877,
            "y": 275
          },
          {
            "x": 12,
            "y": 272
          }
        ],
        "confidence": 1
      }
    ]
  }
}