{
  "page_number": 606,
  "ocr_output": {
    "blocks": [
      {
        "block_text": "స్థాయిలో అది 14 శాతం ఉంది . 2003-2004 సంవత్సరంలో ఉన్నత విద్యకు రూ .887 కోట్లు కేటాయిస్తే , 2008-2009 సంవత్సరంలో తమ ప్రభుత్వం రూ . 1920 కోట్లు కేటాయించింది .",
        "lines": [
          "స్థాయిలో అది 14 శాతం ఉంది . 2003-2004 సంవత్సరంలో ఉన్నత విద్యకు రూ .887 కోట్లు కేటాయిస్తే , 2008-2009 సంవత్సరంలో తమ ప్రభుత్వం రూ . 1920 కోట్లు కేటాయించింది ."
        ],
        "bounding_box": [
          {
            "x": 7,
            "y": 6
          },
          {
            "x": 520,
            "y": 3
          },
          {
            "x": 521,
            "y": 104
          },
          {
            "x": 8,
            "y": 106
          }
        ],
        "confidence": 0.9918132
      }
    ]
  }
}