{
  "page_number": 59,
  "ocr_output": {
    "blocks": [
      {
        "block_text": "రికార్డులోని సాక్ష్యాధారాలను పరిశీలించినట్లుగా రెండు దావాలలోని అప్పీలుదారుడు కొనుగోలు చేసినట్లు చెపుతున్న ఎకరాలు . 1-03 గుంటల భూమి యొక్క గుర్తింపు , ప్రాంతము సంబంధించి స్పష్టమైన వివాదమున్నది . దానినే ఒక అంశముగా కూర్చుట గాని లేక , భూమి యొక్క గుర్తింపు ప్రాంతమునకు సంబంధించిన విషయమును వ్యవహరించుటలో విచారణ న్యాయస్థానము విఫలమైనది.ప్రశ్నార్ధకమైన భూమి యొక్క గుర్తింపు మరియు ఉనికికి సంబంధించిన వివాదము , మరియు , ఓ.ఎస్ .266 / 2005 లోని ఎ - షెడ్యూలు ఆస్తిలో , బి . షెడ్యూలు ఆస్తి భాగమై ఉన్నదేనా అను",
        "lines": [
          "రికార్డులోని సాక్ష్యాధారాలను పరిశీలించినట్లుగా రెండు దావాలలోని అప్పీలుదారుడు కొనుగోలు చేసినట్లు చెపుతున్న ఎకరాలు . 1-03 గుంటల భూమి యొక్క గుర్తింపు , ప్రాంతము సంబంధించి స్పష్టమైన వివాదమున్నది . దానినే ఒక అంశముగా కూర్చుట గాని లేక , భూమి యొక్క గుర్తింపు ప్రాంతమునకు సంబంధించిన విషయమును వ్యవహరించుటలో విచారణ న్యాయస్థానము విఫలమైనది.ప్రశ్నార్ధకమైన భూమి యొక్క గుర్తింపు మరియు ఉనికికి సంబంధించిన వివాదము , మరియు , ఓ.ఎస్ .266 / 2005 లోని ఎ - షెడ్యూలు ఆస్తిలో , బి . షెడ్యూలు ఆస్తి భాగమై ఉన్నదేనా అను"
        ],
        "bounding_box": [
          {
            "x": 7
          },
          {
            "x": 458
          },
          {
            "x": 458,
            "y": 140
          },
          {
            "x": 7,
            "y": 141
          }
        ],
        "confidence": 0.98229116
      }
    ]
  }
}