{
  "page_number": 34,
  "ocr_output": {
    "blocks": [
      {
        "block_text": "కం , అటు లారాధిక గోపీ",
        "lines": [
          "కం , అటు లారాధిక గోపీ"
        ],
        "bounding_box": [
          {
            "x": 44,
            "y": 9
          },
          {
            "x": 290,
            "y": 11
          },
          {
            "x": 290,
            "y": 46
          },
          {
            "x": 44,
            "y": 44
          }
        ],
        "confidence": 0.95693094
      },
      {
        "block_text": "విటు నటు రతికేళి నేలి విడువంగ నిలా కుటిలాలకఁ జేరి తనదు",
        "lines": [
          "విటు నటు రతికేళి నేలి విడువంగ నిలా కుటిలాలకఁ జేరి తనదు"
        ],
        "bounding_box": [
          {
            "x": 90,
            "y": 50
          },
          {
            "x": 473,
            "y": 53
          },
          {
            "x": 472,
            "y": 128
          },
          {
            "x": 89,
            "y": 125
          }
        ],
        "confidence": 0.8638231
      },
      {
        "block_text": "కుటిలత్వ మెఱుంగనీక కూరిమి చెలఁగన్ .",
        "lines": [
          "కుటిలత్వ మెఱుంగనీక కూరిమి చెలఁగన్ ."
        ],
        "bounding_box": [
          {
            "x": 90,
            "y": 144
          },
          {
            "x": 498,
            "y": 146
          },
          {
            "x": 498,
            "y": 182
          },
          {
            "x": 90,
            "y": 180
          }
        ],
        "confidence": 0.96265346
      },
      {
        "block_text": "3",
        "lines": [
          "3"
        ],
        "bounding_box": [
          {
            "x": 602,
            "y": 155
          },
          {
            "x": 618,
            "y": 155
          },
          {
            "x": 618,
            "y": 174
          },
          {
            "x": 602,
            "y": 174
          }
        ],
        "confidence": 0.9052743
      }
    ]
  }
}