{
  "page_number": 385,
  "ocr_output": {
    "blocks": [
      {
        "block_text": "उरणः समुद्राच्या ओहोटीमुळे मोरा मुंबई जलप्रवास दोन तासांसाठी उप्प होणार आहे . शुक्रवारी मोरा बंदरातून मुंबईत जाणारी सायंकाळी ५ ते ८.१५ तर शनिवारी ६.४५ से ८.३० दरम्यान ही लाँच बंद",
        "lines": [
          "उरणः समुद्राच्या ओहोटीमुळे मोरा मुंबई जलप्रवास दोन तासांसाठी उप्प होणार आहे . शुक्रवारी मोरा बंदरातून मुंबईत जाणारी सायंकाळी ५ ते ८.१५ तर शनिवारी ६.४५ से ८.३० दरम्यान ही लाँच बंद"
        ],
        "bounding_box": [
          {
            "x": 2,
            "y": 1
          },
          {
            "x": 106
          },
          {
            "x": 107,
            "y": 71
          },
          {
            "x": 3,
            "y": 72
          }
        ],
        "confidence": 0.8362579
      },
      {
        "block_text": "राहील ,",
        "lines": [
          "राहील ,"
        ],
        "bounding_box": [
          {
            "x": 3,
            "y": 73
          },
          {
            "x": 26,
            "y": 74
          },
          {
            "x": 26,
            "y": 83
          },
          {
            "x": 3,
            "y": 83
          }
        ],
        "confidence": 0.8395802
      }
    ]
  }
}