{
  "page_number": 746,
  "ocr_output": {
    "blocks": [
      {
        "block_text": "ही स्वतःला मालकाच्या हवाली करण्याची गुलामगिरीची मानसिकता केवळ गण्याची नाही . तर काळ्या गोट्यावरील प्रत्येकाची आहे . या मानसिकतेमुळेच मालकाची सत्ता निरंकुशपणे पिढ्यानपिढ्या चालते आहे . लोकांच्या भित्रेपणामागे मालकाने केलेल्या अत्याचाराची पार्श्वभूमी आहे . शेतात पहाऱ्यावर असताना कोल्ह्यांनी शेतात घुसून पंधरावीस ऊसांची नासाडी केली म्हणून सित्याला आपला पाय मालकाकडून तोडून घ्यावा लागला आहे . तर डोळे वर करून मालकाकडे पाहणाऱ्या गण्याला पापणीचे केस उपटण्याची शिक्षा भोगावी लागली आहे . बंधाऱ्यावर काम करताना आजतागायत गण्याची बायको आणि इतर चार अशी पाच माणसे मालकाच्या अत्याचारामुळेच मृत्युमुखी पडली आहेत . या गोष्टीमुळे मालकाविषयी एक भीती लोकांच्या मनात बसली आहे . अशा प्रकारे वेगवेगळ्या प्रसंगातून , संवादातून शोषणकर्त्या मालकाचे पात्र नाटकात",
        "lines": [
          "ही स्वतःला मालकाच्या हवाली करण्याची गुलामगिरीची मानसिकता केवळ गण्याची नाही . तर काळ्या गोट्यावरील प्रत्येकाची आहे . या मानसिकतेमुळेच मालकाची सत्ता निरंकुशपणे पिढ्यानपिढ्या चालते आहे . लोकांच्या भित्रेपणामागे मालकाने केलेल्या अत्याचाराची पार्श्वभूमी आहे . शेतात पहाऱ्यावर असताना कोल्ह्यांनी शेतात घुसून पंधरावीस ऊसांची नासाडी केली म्हणून सित्याला आपला पाय मालकाकडून तोडून घ्यावा लागला आहे . तर डोळे वर करून मालकाकडे पाहणाऱ्या गण्याला पापणीचे केस उपटण्याची शिक्षा भोगावी लागली आहे . बंधाऱ्यावर काम करताना आजतागायत गण्याची बायको आणि इतर चार अशी पाच माणसे मालकाच्या अत्याचारामुळेच मृत्युमुखी पडली आहेत . या गोष्टीमुळे मालकाविषयी एक भीती लोकांच्या मनात बसली आहे . अशा प्रकारे वेगवेगळ्या प्रसंगातून , संवादातून शोषणकर्त्या मालकाचे पात्र नाटकात"
        ],
        "bounding_box": [
          {
            "x": 7,
            "y": 4
          },
          {
            "x": 1127,
            "y": 3
          },
          {
            "x": 1127,
            "y": 492
          },
          {
            "x": 7,
            "y": 493
          }
        ],
        "confidence": 0.96034104
      }
    ]
  }
}