{
  "page_number": 144,
  "ocr_output": {
    "blocks": [
      {
        "block_text": "कीर्तनामुळे श्रोत्यांची कल्पनाशक्ती चाळवली जाते . अशीच कल्पनाशक्ती चाळकऱ्यांची - पत्नीची नानाची चाळवली गेल्याचे दिसेल . उदाहरणार्थ , चाळकऱ्यांची कल्पनाशक्ती शेजारच्या जोश्यांच्या बंडूचा चेहरा व भाऊरावांचा चेहरा यात कसे साम्य आहे या संदर्भात जागृत होते . पत्नीची कल्पनाशक्ती डावीकडून तिसरा कोण ? तर नानाची कल्पनाशक्ती मी कोणाचा आहे ? यासंदर्भात विचार केला गेला आहे .",
        "lines": [
          "कीर्तनामुळे श्रोत्यांची कल्पनाशक्ती चाळवली जाते . अशीच कल्पनाशक्ती चाळकऱ्यांची - पत्नीची नानाची चाळवली गेल्याचे दिसेल . उदाहरणार्थ , चाळकऱ्यांची कल्पनाशक्ती शेजारच्या जोश्यांच्या बंडूचा चेहरा व भाऊरावांचा चेहरा यात कसे साम्य आहे या संदर्भात जागृत होते . पत्नीची कल्पनाशक्ती डावीकडून तिसरा कोण ? तर नानाची कल्पनाशक्ती मी कोणाचा आहे ? यासंदर्भात विचार केला गेला आहे ."
        ],
        "bounding_box": [
          {
            "x": 6,
            "y": 9
          },
          {
            "x": 1174,
            "y": 3
          },
          {
            "x": 1176,
            "y": 281
          },
          {
            "x": 8,
            "y": 287
          }
        ],
        "confidence": 0.9535407
      }
    ]
  }
}