{
  "page_number": 159,
  "ocr_output": {
    "blocks": [
      {
        "block_text": "13-5-45 .",
        "lines": [
          "13-5-45 ."
        ],
        "bounding_box": [
          {
            "x": 23,
            "y": 24
          },
          {
            "x": 143,
            "y": 22
          },
          {
            "x": 143,
            "y": 48
          },
          {
            "x": 23,
            "y": 50
          }
        ],
        "confidence": 0.918623
      }
    ]
  }
}