{
  "page_number": 347,
  "ocr_output": {
    "blocks": [
      {
        "block_text": "இதைக் கருத்தில்கொண்டே குறைகடத்திகளுக்கென தனிக் கொள்கையை தமிழக அரசு இந்த மாநாட்டில் வெளியிட்டுள்ளது .",
        "lines": [
          "இதைக் கருத்தில்கொண்டே குறைகடத்திகளுக்கென தனிக் கொள்கையை தமிழக அரசு இந்த மாநாட்டில் வெளியிட்டுள்ளது ."
        ],
        "bounding_box": [
          {
            "x": 4
          },
          {
            "x": 186
          },
          {
            "x": 186,
            "y": 61
          },
          {
            "x": 4,
            "y": 61
          }
        ],
        "confidence": 0.9796009
      }
    ]
  }
}