{
  "page_number": 320,
  "ocr_output": {
    "blocks": [
      {
        "block_text": "வள்ளுவம் வலியுறுத்துகிறது .",
        "lines": [
          "வள்ளுவம் வலியுறுத்துகிறது ."
        ],
        "bounding_box": [
          {
            "x": 3,
            "y": 1
          },
          {
            "x": 139,
            "y": 2
          },
          {
            "x": 139,
            "y": 15
          },
          {
            "x": 3,
            "y": 15
          }
        ],
        "confidence": 0.98564625
      }
    ]
  }
}