{
  "page_number": 93,
  "ocr_output": {
    "blocks": [
      {
        "block_text": "ପାର୍ଶ୍ୱଦରୁ ବାଲୁଗାଁ । ଆଖ‌ିବା ପାଇଁ ସିମୁଦ୍ରା ସାଧ୍ୟ ବଡ଼ବନ ରହିଛି । ପାଶଦ ଗୁଜାସାହେବ ଏହି ସାଧର ମାନକ । ବମାନ ନୃସିଂହରଣ ମିଶ୍ର ନାମକ ଜଣେ ଭଦ୍ରଲେକ ଏହି ସାଧ୍ୟ ପଞ୍ଚୁ ।",
        "lines": [
          "ପାର୍ଶ୍ୱଦରୁ ବାଲୁଗାଁ । ଆଖ‌ିବା ପାଇଁ ସିମୁଦ୍ରା ସାଧ୍ୟ ବଡ଼ବନ ରହିଛି । ପାଶଦ ଗୁଜାସାହେବ ଏହି ସାଧର ମାନକ । ବମାନ ନୃସିଂହରଣ ମିଶ୍ର ନାମକ ଜଣେ ଭଦ୍ରଲେକ ଏହି ସାଧ୍ୟ ପଞ୍ଚୁ ।"
        ],
        "bounding_box": [
          {
            "x": 3
          },
          {
            "x": 266
          },
          {
            "x": 266,
            "y": 94
          },
          {
            "x": 3,
            "y": 95
          }
        ],
        "confidence": 0.57508534
      },
      {
        "block_text": "ନେଇଛନ୍ତି । କିନ୍ତୁ ଲୋକମାନଙ୍କୁ ନେବା ଆଣିବାରେ ଠିକ୍ ସଂୟୁ ରଖୁ ନାହାରୁ । ଏହା ଛଡ଼ା ବାଲୁଗାଁରୁ ପାଶ୍ଚାଦର ବିର ଜାଗାରୁ ଅନ୍ୟ ଡ଼ଙ୍ଗାରେ ଯେ ପାଶ୍ଚା ହେଉଛି , ଏହି ମୁଦାରଙ୍କ ଗୁଇ ଜଣେ ବାଲିଗାଁ । ତରଫରେ ରହ ଜଣ ପିସ୍ଥ ଦୁଇଅଣା ହାରରେ ଜବରଦସ୍ତ ଧମକ ଚମକ ଦେଖାଇ ନେଇ",
        "lines": [
          "ନେଇଛନ୍ତି । କିନ୍ତୁ ଲୋକମାନଙ୍କୁ ନେବା ଆଣିବାରେ ଠିକ୍ ସଂୟୁ ରଖୁ ନାହାରୁ । ଏହା ଛଡ଼ା ବାଲୁଗାଁରୁ ପାଶ୍ଚାଦର ବିର ଜାଗାରୁ ଅନ୍ୟ ଡ଼ଙ୍ଗାରେ ଯେ ପାଶ୍ଚା ହେଉଛି , ଏହି ମୁଦାରଙ୍କ ଗୁଇ ଜଣେ ବାଲିଗାଁ । ତରଫରେ ରହ ଜଣ ପିସ୍ଥ ଦୁଇଅଣା ହାରରେ ଜବରଦସ୍ତ ଧମକ ଚମକ ଦେଖାଇ ନେଇ"
        ],
        "bounding_box": [
          {
            "x": 6,
            "y": 95
          },
          {
            "x": 268,
            "y": 94
          },
          {
            "x": 269,
            "y": 235
          },
          {
            "x": 7,
            "y": 236
          }
        ],
        "confidence": 0.7016405
      },
      {
        "block_text": "ଯାଉଛନ୍ତି । ଶଲ୍‌ଳାରେ ଡଙ୍ଗା ଚଲାଉ ଥୁବା ଅନ୍ୟ ନାଉରୀମାନେ ବ ଏହି ମୁକ୍ତାଦାରଙ୍କ ଗୁଇ ସ୍ଵାଗ ବଡ଼ ବ୍ୟତିବ୍ୟଧି ହେଉଛି । ପ୍ରାଇଭେ୪ ଘା୪ ଥିବା ଯୋଗେ ସର୍ବସାଧାରଣଙ୍କର ଶେଷ କ୍ଷଣି ଘଞ୍ଚୁଛି । ବର୍ତ୍ତମାନ ସେଚପ୍ରତିନ୍ ସରକାର ଏହି ସାନ୍ତୁ ।",
        "lines": [
          "ଯାଉଛନ୍ତି । ଶଲ୍‌ଳାରେ ଡଙ୍ଗା ଚଲାଉ ଥୁବା ଅନ୍ୟ ନାଉରୀମାନେ ବ ଏହି ମୁକ୍ତାଦାରଙ୍କ ଗୁଇ ସ୍ଵାଗ ବଡ଼ ବ୍ୟତିବ୍ୟଧି ହେଉଛି । ପ୍ରାଇଭେ୪ ଘା୪ ଥିବା ଯୋଗେ ସର୍ବସାଧାରଣଙ୍କର ଶେଷ କ୍ଷଣି ଘଞ୍ଚୁଛି । ବର୍ତ୍ତମାନ ସେଚପ୍ରତିନ୍ ସରକାର ଏହି ସାନ୍ତୁ ।"
        ],
        "bounding_box": [
          {
            "x": 10,
            "y": 238
          },
          {
            "x": 280,
            "y": 240
          },
          {
            "x": 279,
            "y": 356
          },
          {
            "x": 9,
            "y": 355
          }
        ],
        "confidence": 0.5586234
      }
    ]
  }
}