{
  "page_number": 300,
  "ocr_output": {
    "blocks": [
      {
        "block_text": "ସବୁଜ ଚେତନା : କାଳର ପରିପ୍ରେକ୍ଷୀତରେ ଏକ ନୂତନତାର ସ୍ବାକ୍ଷର :",
        "lines": [
          "ସବୁଜ ଚେତନା : କାଳର ପରିପ୍ରେକ୍ଷୀତରେ ଏକ ନୂତନତାର ସ୍ବାକ୍ଷର :"
        ],
        "bounding_box": [
          {
            "x": 10,
            "y": 4
          },
          {
            "x": 528,
            "y": 4
          },
          {
            "x": 528,
            "y": 27
          },
          {
            "x": 10,
            "y": 27
          }
        ],
        "confidence": 0.9848424
      }
    ]
  }
}