{
  "page_number": 811,
  "ocr_output": {
    "blocks": [
      {
        "block_text": "ଯେକୌଣସି ଯାନ ଚଳାଇ ରାସ୍ତାରେ ଯିବା ସମୟରେ ମୋବାଇଲ ଫୋନରେ କଥା ହେବା ଉଚିତ ନୁହେଁ କିଂବା ଇଅର ଫୋନ୍ ଲଗାଇ ସଙ୍ଗୀତ ଶୁଣିବା ଉଚିତ ନୁହେଁ ।",
        "lines": [
          "ଯେକୌଣସି ଯାନ ଚଳାଇ ରାସ୍ତାରେ ଯିବା ସମୟରେ ମୋବାଇଲ ଫୋନରେ କଥା ହେବା ଉଚିତ ନୁହେଁ କିଂବା ଇଅର ଫୋନ୍ ଲଗାଇ ସଙ୍ଗୀତ ଶୁଣିବା ଉଚିତ ନୁହେଁ ।"
        ],
        "bounding_box": [
          {
            "x": 4,
            "y": 2
          },
          {
            "x": 384,
            "y": 2
          },
          {
            "x": 384,
            "y": 46
          },
          {
            "x": 4,
            "y": 46
          }
        ],
        "confidence": 0.9826932
      }
    ]
  }
}