{
  "page_number": 307,
  "ocr_output": {
    "blocks": [
      {
        "block_text": "ਗਣਿਤ ਵਿਸ਼ੇ ਦੇ ਅਧਿਆਪਕ ਨੇ ਬੋਰਡ ' ਤੇ ਇੱਕ ਆਕ੍ਰਿਤੀ ਬਣਾਈ ਜਿਸਦੀਆਂ ਆਹਮਣੇ ਸਾਹਮਣੇ ਦੀਆਂ ਭੁਜਾਵਾਂ ਬਰਾਬਰ ਹਨ । ਉਸ ਆਕ੍ਰਿਤੀ ਦਾ ਨਾਂ ਦੱਸੋ ?",
        "lines": [
          "ਗਣਿਤ ਵਿਸ਼ੇ ਦੇ ਅਧਿਆਪਕ ਨੇ ਬੋਰਡ ' ਤੇ ਇੱਕ ਆਕ੍ਰਿਤੀ ਬਣਾਈ ਜਿਸਦੀਆਂ ਆਹਮਣੇ ਸਾਹਮਣੇ ਦੀਆਂ ਭੁਜਾਵਾਂ ਬਰਾਬਰ ਹਨ । ਉਸ ਆਕ੍ਰਿਤੀ ਦਾ ਨਾਂ ਦੱਸੋ ?"
        ],
        "bounding_box": [
          {
            "x": 102,
            "y": 11
          },
          {
            "x": 1359,
            "y": 5
          },
          {
            "x": 1359,
            "y": 96
          },
          {
            "x": 102,
            "y": 102
          }
        ],
        "confidence": 0.93901426
      },
      {
        "block_text": "14 .",
        "lines": [
          "14 ."
        ],
        "bounding_box": [
          {
            "x": 17,
            "y": 18
          },
          {
            "x": 54,
            "y": 18
          },
          {
            "x": 54,
            "y": 41
          },
          {
            "x": 17,
            "y": 41
          }
        ],
        "confidence": 0.9904294
      }
    ]
  }
}